bakelite/__init__.py
bakelite/generator/__init__.py
bakelite/generator/cli.py
bakelite/generator/cpptiny.py
bakelite/generator/parser.py
bakelite/generator/protodef.lark
bakelite/generator/python.py
bakelite/generator/runtimes/cpptiny/cobs.h
bakelite/generator/runtimes/cpptiny/crc.h
bakelite/generator/runtimes/cpptiny/declarations.h
bakelite/generator/runtimes/cpptiny/serializer.h
bakelite/generator/templates/cpptiny-bakelite.h.j2
bakelite/generator/templates/cpptiny.h.j2
bakelite/generator/templates/python.py.j2
bakelite/generator/types.py
bakelite/generator/util.py
bakelite/proto/__init__.py
bakelite/proto/crc.py
bakelite/proto/framing.py
bakelite/proto/runtime.py
bakelite/proto/serialization.py
bakelite/py.typed
bakelite/tests/__init__.py
bakelite/tests/conftest.py
bakelite/tests/generator/.gitignore
bakelite/tests/generator/Makefile
bakelite/tests/generator/cpptiny-framing.cpp
bakelite/tests/generator/cpptiny-protocol.cpp
bakelite/tests/generator/cpptiny-serialization.cpp
bakelite/tests/generator/cpptiny.h
bakelite/tests/generator/doctest.h
bakelite/tests/generator/proto.bakelite
bakelite/tests/generator/struct.bakelite
bakelite/tests/proto/protocol.ex
bakelite/tests/proto/struct.ex
bakelite/tests/proto/test_framing.py
bakelite/tests/proto/test_protocol.py
bakelite/tests/proto/test_serialization.py
bakelite/tests/proto/test_validation.py
bakelite-0.3.0.dist-info/entry_points.txt
bakelite-0.3.0.dist-info/LICENSE.md
bakelite-0.3.0.dist-info/WHEEL
bakelite-0.3.0.dist-info/METADATA
bakelite-0.3.0.dist-info/RECORD
