Metadata-Version: 2.1
Name: bakelite
Version: 0.3.0
Summary: A utility that makes it simple to communicate with your firmware.
Home-page: https://pypi.org/project/bakelite
License: MIT
Author: Brendan Powers
Author-email: brendan0powers@gmail.com
Requires-Python: >=3.8,<4.0
Classifier: Development Status :: 3 - Alpha
Classifier: License :: OSI Approved :: MIT License
Classifier: Natural Language :: English
Classifier: Operating System :: OS Independent
Classifier: Programming Language :: Python
Classifier: Programming Language :: Python :: 3
Classifier: Programming Language :: Python :: 3.8
Classifier: Programming Language :: Python :: 3.9
Classifier: Programming Language :: Python :: 3.10
Classifier: Programming Language :: Python :: 3
Classifier: Programming Language :: Python :: 3.8
Classifier: Topic :: Scientific/Engineering :: Interface Engine/Protocol Translator
Classifier: Topic :: Software Development :: Embedded Systems
Classifier: Topic :: Software Development :: Libraries
Requires-Dist: bitstring (>=3.1.7,<4.0.0)
Requires-Dist: click (>=8.0.3,<9.0.0)
Requires-Dist: dataclasses-json (>=0.5.2,<0.6.0)
Requires-Dist: jinja2 (>=3,<4)
Requires-Dist: lark (>=0.12.0,<0.13.0)
Project-URL: Documentation, https://bakelite.readthedocs.io
Project-URL: Repository, https://github.com/brendan0powers/bakelite
